bayesmsd/__init__.py
bayesmsd/cython_imports.py
bayesmsd/deco.py
bayesmsd/fit.py
bayesmsd/fitgroup.py
bayesmsd/fitsum.py
bayesmsd/gp.py
bayesmsd/lib.py
bayesmsd/parameters.py
bayesmsd/profiler.py
bayesmsd/src/gp.c
bayesmsd/src/gp_py.py
bayesmsd-0.1.7.dist-info/licenses/LICENSE
bayesmsd-0.1.7.dist-info/METADATA
bayesmsd-0.1.7.dist-info/WHEEL
bayesmsd-0.1.7.dist-info/top_level.txt
bayesmsd-0.1.7.dist-info/RECORD
