Metadata-Version: 2.4
Name: bayesmsd
Version: 0.1.7
Summary: Bayesian MSD fitting
Author-email: Simon Grosse-Holz <sgh256@mit.edu>
License: MIT License
Project-URL: Homepage, https://github.com/OpenTrajectoryAnalysis/bayesmsd
Project-URL: Documentation, https://bayesmsd.readthedocs.org/en/latest
Project-URL: Bug Tracker, https://github.com/OpenTrajectoryAnalysis/bayesmsd/issues
Classifier: Programming Language :: Python :: 3
Classifier: License :: OSI Approved :: MIT License
Classifier: Operating System :: OS Independent
Requires-Python: >=3.7
License-File: LICENSE
Requires-Dist: noctiluca>=0
Requires-Dist: rouse>=0
Requires-Dist: numpy<2,>=1.20
Requires-Dist: scipy>=1.7
Requires-Dist: tqdm>=4
Requires-Dist: matplotlib>=3.4
Dynamic: license-file
